fibery/__init__.py
fibery/client/__init__.py
fibery/client/base.py
fibery/client/entity.py
fibery/client/fibery.py
fibery/client/schema.py
fibery/client/utils.py
fibery/client/webhook.py
fibery/conf.py
fibery/console/__init__.py
fibery/console/app.py
fibery/console/commands/__init__.py
fibery/console/commands/api.py
fibery/console/commands/auth.py
fibery/console/commands/auth_token.py
fibery/console/commands/base.py
fibery/console/commands/config.py
fibery/console/commands/config_settings.py
fibery/console/commands/describe.py
fibery/console/commands/js/token_create.js
fibery/console/commands/js/token_delete.js
fibery/console/commands/js/token_list.js
fibery/console/commands/pyppeteer_actions.py
fibery/console/commands/utils.py
fibery/console/main.py
fibery/enums.py
fibery/models.py
fibery-0.4.1.dist-info/entry_points.txt
fibery-0.4.1.dist-info/WHEEL
fibery-0.4.1.dist-info/METADATA
fibery-0.4.1.dist-info/RECORD
