Metadata-Version: 2.1
Name: fibery
Version: 0.4.1
Summary: Fibery.io Python SDK
Home-page: https://github.com/sergio-bershadsky/fibery
Author: Sergio Bershadsky
Author-email: sergio.bershadsky@gmail.com
Requires-Python: >=3.7,<4.0
Classifier: Programming Language :: Python :: 3
Classifier: Programming Language :: Python :: 3.7
Classifier: Programming Language :: Python :: 3.8
Classifier: Programming Language :: Python :: 3.9
Requires-Dist: PyYAML (>=5.4.1,<6.0.0)
Requires-Dist: aiohttp (>=3.7.4,<4.0.0)
Requires-Dist: colorama (>=0.4.4,<0.5.0)
Requires-Dist: pydantic (>=1.8.1,<2.0.0)
Requires-Dist: pyppeteer (>=0.2.5,<0.3.0)
Requires-Dist: requests (>=2.25.1,<3.0.0)
Requires-Dist: tabulate (>=0.8.9,<0.9.0)
Requires-Dist: typer (>=0.3.2,<0.4.0)
Project-URL: Repository, https://github.com/sergio-bershadsky/fibery
